{"tyontekijat":[{"ID":"20", "Etunimi":"Markus", "Sukunimi":"Ranta", "Puhelin":"0103957839", "Email":"mranta@huolto.fi", "Tila":"Vapaa", "Rooli":"huoltohenkilo"},{"ID":"27", "Etunimi":"Henri", "Sukunimi":"Uovinen", "Puhelin":"040 951 3669", "Email":"huovinen@jotain.fi", "Tila":"Vapaa", "Rooli":"huoltohenkilo"},{"ID":"19", "Etunimi":"Juho", "Sukunimi":"Nieminen", "Puhelin":"0501238723", "Email":"jnieminen@huolto.fi", "Tila":"Vapaa", "Rooli":"huoltohenkilo"},{"ID":"30", "Etunimi":"Mikko", "Sukunimi":"Virtanen", "Puhelin":"0400 555 667", "Email":"mvirtanen@jotain.fi", "Tila":"Vapaa", "Rooli":"huoltohenkilo"},{"ID":"21", "Etunimi":"Anna ", "Sukunimi":"Kivelä", "Puhelin":"0401239851", "Email":"akivelä@huolto.fi", "Tila":"Vapaa", "Rooli":"huoltohenkilo"},{"ID":"23", "Etunimi":"Ville", "Sukunimi":"Laine", "Puhelin":"0400 454969", "Email":"vlaine@toimisto.fi", "Tila":"Vapaa", "Rooli":"toimistohenkilo"},{"ID":"26", "Etunimi":"Sari", "Sukunimi":"Lahti", "Puhelin":"045 344 8999", "Email":"slahti@jotain.fi", "Tila":"Vapaa", "Rooli":"toimistohenkilo"},{"ID":"28", "Etunimi":"Tuuli", "Sukunimi":"Oinas", "Puhelin":"0400 454 969", "Email":"toinas@jotain.fi", "Tila":"Vapaa", "Rooli":"toimistohenkilo"}]}